README.md
setup.py
Flask_Account.egg-info/PKG-INFO
Flask_Account.egg-info/SOURCES.txt
Flask_Account.egg-info/dependency_links.txt
Flask_Account.egg-info/top_level.txt
flask_account/__init__.py
flask_account/core.py
flask_account/model.py